Metadata-Version: 2.1
Name: docassemble.spot
Version: 0.0.1
Summary: Provides a datatype for legal issue spotting using the Spot API.
Home-page: https://docassemble.org
Author: Jonathan Pyle
Author-email: jhpyle@gmail.com
License: The MIT License (MIT)
Platform: UNKNOWN
